pyscal2-2.10.21.dist-info/RECORD
pyscal2-2.10.21.dist-info/LICENSE
pyscal2-2.10.21.dist-info/WHEEL
pyscal2-2.10.21.dist-info/top_level.txt
pyscal2-2.10.21.dist-info/METADATA
pyscal2-2.10.21.data/headers/atom.h
pyscal2-2.10.21.data/headers/voro++.hh
pyscal2-2.10.21.data/headers/system.h
pyscal/misc.py
pyscal/catom.cpython-39-darwin.so
pyscal/csystem.cpython-39-darwin.so
pyscal/crystal_structures.py
pyscal/__init__.py
pyscal/core.py
pyscal/trajectory.py
pyscal/visualization.py
pyscal/traj_process.py
pyscal/routines.py
pyscal/formats/ase.py
pyscal/formats/__init__.py
pyscal/formats/mdtraj.py
pyscal/formats/vasp.py
pyscal/formats/lammps.py
